redcodegen/#main.py#
redcodegen/#seeds.py#
redcodegen/__init__.py
redcodegen/constants.py
redcodegen/data/__init__.py
redcodegen/data/scenario_dow.jsonl
redcodegen/generator.py
redcodegen/kernels/__init__.py
redcodegen/kernels/kernel.py
redcodegen/kernels/rephrase.py
redcodegen/main.py
redcodegen/scenarios.py
redcodegen/seeds.py
redcodegen/uncertainty.py
redcodegen/validator.py
redcodegen-0.1.2.dist-info/WHEEL
redcodegen-0.1.2.dist-info/entry_points.txt
redcodegen-0.1.2.dist-info/METADATA
redcodegen-0.1.2.dist-info/RECORD
