Metadata-Version: 2.3
Name: redcodegen
Version: 0.1.2
Summary: Add your description here
Requires-Dist: click>=8.0.0
Requires-Dist: cwe2>=3.0.0
Requires-Dist: dspy>=3.0.3
Requires-Dist: jsonlines>=4.0.0
Requires-Dist: pandas>=2.3.3
Requires-Dist: python-dotenv>=1.1.1
Requires-Dist: rich>=14.2.0
Requires-Dist: rich-click>=1.9.3
Requires-Dist: scipy>=1.16.3
Requires-Dist: semgrep>=1.86.0
Requires-Python: >=3.11
